<xml xmlns="http://www.w3.org/1999/xhtml"><block type="box" id="q`2_=|dBa]lGf)FP3B%B" x="9" y="53"><value name="type"><block type="text" id="9DT}#6qfkQ!B98Gb=l3^"><field name="TEXT">1</field></block></value><value name="width"><block type="math_number" id="Uu36Q_y#roS2J6/^m@.;"><field name="NUM">1</field></block></value><value name="height"><block type="math_number" id="kVbC8}aj@nrQ!CP,pJFJ"><field name="NUM">1</field></block></value><value name="depth"><block type="math_number" id="F]{k@o@wP@q,~_x+gzEL"><field name="NUM">1</field></block></value></block></xml>